README.md
setup.py
rn_installer/__init__.py
rn_installer/cli.py
rn_installer.egg-info/PKG-INFO
rn_installer.egg-info/SOURCES.txt
rn_installer.egg-info/dependency_links.txt
rn_installer.egg-info/entry_points.txt
rn_installer.egg-info/requires.txt
rn_installer.egg-info/top_level.txt