Metadata-Version: 2.4
Name: rn_installer
Version: 0.1
Requires-Dist: click
Requires-Dist: requests
Requires-Dist: tqdm
Requires-Dist: plumbum
Requires-Dist: python-dotenv
Requires-Dist: rich
Dynamic: description
Dynamic: description-content-type
Dynamic: requires-dist
